ahgp/__init__.py
ahgp/gp/__init__.py
ahgp/gp/gp_helper.py
ahgp/inference/__init__.py
ahgp/inference/hyperparam.py
ahgp/inference/predict.py
ahgp/nn/__init__.py
ahgp/nn/gp_sm_2att.py
ahgp/nn/gp_sm_2att_nomu.py
ahgp/nn/module.py
model/__init__.py
model/gp/__init__.py
model/gp/gp_helper.py
model/inference/__init__.py
model/inference/hyperparam.py
model/inference/predict.py
model/nn/__init__.py
model/nn/gp_sm_2att.py
model/nn/gp_sm_2att_nomu.py
model/nn/module.py
amor_hyp_gp-0.1.1.dist-info/LICENSE.md
amor_hyp_gp-0.1.1.dist-info/METADATA
amor_hyp_gp-0.1.1.dist-info/WHEEL
amor_hyp_gp-0.1.1.dist-info/top_level.txt
amor_hyp_gp-0.1.1.dist-info/RECORD
