Metadata-Version: 2.1
Name: amor-hyp-gp
Version: 0.1.1
Summary: Task-Agnostic Amortized Inference of Gaussian Process Hyperparameters (AHGP)
Home-page: https://github.com/PrincetonLIPS/AHGP
Author: Sulin Liu
Author-email: sulinl@princeton.edu
License: MIT
Platform: UNKNOWN
Classifier: Development Status :: 3 - Alpha
Classifier: Intended Audience :: Science/Research
Classifier: License :: OSI Approved :: MIT License
